  {
  "mmid": 54,
  "songName": "FooFoo (ဖူးဖူး)",
  "artistName": "Vannex",
  "albumName": "Genius & Madness",
  "genre": "Hip Hop, Rap",
  "spotifyTrackId": "3GVhGI93M1JoGXXX2OxIjQ",
  "imageLink": "https://i.scdn.co/image/ab67616d00001e02d52c6ff1b6681f83b3cf9a64",
  "appleMusicLink": "https://music.apple.com/ca/song/foo-foo/1752595019",
  "spotifyLink": "https://open.spotify.com/track/3GVhGI93M1JoGXXX2OxIjQ",
  "youtubeLink": "https://www.youtube.com/watch?v=Tma1hFhiQMs",
  "about": "\"FooFoo,\" is a hip hop/rap song about confidence, resilience, and rising above the negativity and criticism from others while staying true to yourself ",
  "whenToListen": "When you need a boost of confidence and want to shut down the haters with bold energy.",
  "lyrics": "Prince Vannex on the beat let's go\nTalking bout me lil bro yo what\nLil bro you a foofoo\nAye aye\nA re A re\nPrince on the beat oh sh*t what\nLet's go Let's go\n\nTalking bout me lil bro you a foofoo\nPrince on the beat oh sh*t it's coo cool\nHaters mad like bro I don't mean to\nCrying they crying bro who you?\nVannex on the beat yo bro in ring ru \nDress leh outfit vel maw an care chu?\nNow we winning rawn let pawh tum su\nD*ckride min rawn um phak tum ru!\n\nTalking bout me lil bro you a foofoo\nPrince on the beat oh sh*t it's coo cool\nHaters mad like bro I don't mean to\nCrying they crying bro who you?\nVannex on the beat yo bro in ring ru \nDress leh outfit vel maw an care chu?\nNow we winning rawn let pawh tum su\nD*ckride min rawn um phak tum ru!\n\nI’m back with the heat Yea \nI own this shit from down below like Roddy Rich \nSaid I can’t so I take this risk\nI’ll put you down on my haters List\nCause u do not deserve no diss\nSo go on and shake that hip\nThis jersey drill this jersey hit\nI’m healing myself likes the one from Chris\n\nVannex u don’t gotta move this mad\nWhy??? U making them look so bad\nHuh??? What do u mean by that?? \nThem drill rappers who really can’t rap \nThem trap trappers who really don’t trap\nThem cap cappers who really gon cap \nSome of the haters who really don’t hate\nThey just wanted the spot or they wanted the place\n\nShit Rawn Drop ve zuk like Blow \nMike Mas Peng my dawg my Bros\nHornBills got my back 24\nM for MIZO boyz let’s go!!!\n\nShit Rawn Drop ve zuk like Blow \nMike Mas Peng my dawg my Bros\nHornBills got my back 24\nM for MIZO boyz let’s go!!!\n\nTalking bout me lil bro you a foofoo\nPrince on the beat oh sh*t it's coo cool\nHaters mad like bro I don't mean to\nCrying they crying bro who you?\nVannex on the beat yo bro in ring ru \nDress leh outfit vel maw an care chu?\nNow we winning rawn let pawh tum su\nD*ckride min rawn um phak tum ru!\n\nTalking bout me lil bro you a foofoo\nPrince on the beat oh sh*t it's coo cool\nHaters mad like bro I don't mean to\nCrying they crying bro who you?\nVannex on the beat yo bro in ring ru \nDress leh outfit vel maw an care chu?\nNow we winning rawn let pawh tum su\nD*ckride min rawn um phak tum ru!\n\nNew York Drill?\nUk Drill?\nNah Bro this MYANMAR Drill\nLet them know that this shyt getting real\nIs our time yea is time to reveal\n\nNewYork Drill?\nUk Drill?\nNah Bro this BURMA Drill\nLet them know that this shyt getting real\nIs our time yea is time to reveal\n\nTalking bout me lil bro you a foofoo\nPrince on the beat oh sh*t it's coo cool\nHaters mad like bro I don't mean to\nCrying they crying bro who you?\nVannex on the beat yo bro in ring ru \nDress leh outfit vel maw an care chu?\nNow we winning rawn let pawh tum su\nD*ckride min rawn um phak tum ru!\n\nShit Rawn Drop ve zuk like Blow \nMike Mas Peng my dawg my Bros\nHornBills got my back 24\nM for MIZO boyz let’s go!!!\n\nShit Rawn Drop ve zuk like Blow \nMike Mas Peng my dawg my Bros\nHornBills got my back 24\nM for MIZO boyz let’s go!!!\n",
  "romanized": "Prince Vannex on the beat let's go\nTalking bout me lil bro yo what\nLil bro you a foofoo\nAye aye\nA re A re\nPrince on the beat oh sh*t what\nLet's go Let's go\n\nTalking bout me lil bro you a foofoo\nPrince on the beat oh sh*t it's coo cool\nHaters mad like bro I don't mean to\nCrying they crying bro who you?\nVannex on the beat yo bro in ring ru \nDress leh outfit vel maw an care chu?\nNow we winning rawn let pawh tum su\nD*ckride min rawn um phak tum ru!\n\nTalking bout me lil bro you a foofoo\nPrince on the beat oh sh*t it's coo cool\nHaters mad like bro I don't mean to\nCrying they crying bro who you?\nVannex on the beat yo bro in ring ru \nDress leh outfit vel maw an care chu?\nNow we winning rawn let pawh tum su\nD*ckride min rawn um phak tum ru!\n\nI’m back with the heat Yea \nI own this shit from down below like Roddy Rich \nSaid I can’t so I take this risk\nI’ll put you down on my haters List\nCause u do not deserve no diss\nSo go on and shake that hip\nThis jersey drill this jersey hit\nI’m healing myself likes the one from Chris\n\nVannex u don’t gotta move this mad\nWhy??? U making them look so bad\nHuh??? What do u mean by that?? \nThem drill rappers who really can’t rap \nThem trap trappers who really don’t trap\nThem cap cappers who really gon cap \nSome of the haters who really don’t hate\nThey just wanted the spot or they wanted the place\n\nShit Rawn Drop ve zuk like Blow \nMike Mas Peng my dawg my Bros\nHornBills got my back 24\nM for MIZO boyz let’s go!!!\n\nShit Rawn Drop ve zuk like Blow \nMike Mas Peng my dawg my Bros\nHornBills got my back 24\nM for MIZO boyz let’s go!!!\n\nTalking bout me lil bro you a foofoo\nPrince on the beat oh sh*t it's coo cool\nHaters mad like bro I don't mean to\nCrying they crying bro who you?\nVannex on the beat yo bro in ring ru \nDress leh outfit vel maw an care chu?\nNow we winning rawn let pawh tum su\nD*ckride min rawn um phak tum ru!\n\nTalking bout me lil bro you a foofoo\nPrince on the beat oh sh*t it's coo cool\nHaters mad like bro I don't mean to\nCrying they crying bro who you?\nVannex on the beat yo bro in ring ru \nDress leh outfit vel maw an care chu?\nNow we winning rawn let pawh tum su\nD*ckride min rawn um phak tum ru!\n\nNew York Drill?\nUk Drill?\nNah Bro this MYANMAR Drill\nLet them know that this shyt getting real\nIs our time yea is time to reveal\n\nNewYork Drill?\nUk Drill?\nNah Bro this BURMA Drill\nLet them know that this shyt getting real\nIs our time yea is time to reveal\n\nTalking bout me lil bro you a foofoo\nPrince on the beat oh sh*t it's coo cool\nHaters mad like bro I don't mean to\nCrying they crying bro who you?\nVannex on the beat yo bro in ring ru \nDress leh outfit vel maw an care chu?\nNow we winning rawn let pawh tum su\nD*ckride min rawn um phak tum ru!\n\nShit Rawn Drop ve zuk like Blow \nMike Mas Peng my dawg my Bros\nHornBills got my back 24\nM for MIZO boyz let’s go!!!\n\nShit Rawn Drop ve zuk like Blow \nMike Mas Peng my dawg my Bros\nHornBills got my back 24\nM for MIZO boyz let’s go!!!\n",
  "burmese": "မင်းသား Vannex တေးသွားပေါ်မှာ လာသွားစို့\nငါ့အတင်းပြောနေတဲ့ညီလေး ဘာတုန်းဟ\nညီလေး မင်းက ဖူးဖူး\nအေး အေး\nအာရယ် အာရယ်\nမင်းသားက တေးသွားပေါ်မှာ ဟာ ချီးပဲ ဘာလဲ\nသွားစို့ သွားစို့\n\nငါ့အတင်းပြောနေတဲ့ညီလေး မင်းက ဖူးဖူး\nမင်းသားက တေးသွားပေါ်မှာ ဟာ ချီး မိုက်တယ် မိုက်တယ်\nမုန်းတဲ့သူ မုန်းနေတယ် ငါ မရည်ရွယ်ပါဘူး\nငိုနေတယ် သူတို့ ငိုနေတယ်မင်း မင်းဘယ်သူလဲ\nVannex တေးသွားနဲ့ဂေါ်နေပြီ အဆင်သင့်ပြင်\nမင်း အဲ့အဝတ်အစားကို ဂရုစိုက်တယ်မလား\nခုငါနိုင်နေပြီ ဘယ်တော့မှပြန်လာဖို့ မကြိုးစားနဲ့\nငါ့ကို မှီအောင်သာ ကြိုးစား\n\nငါ့အတင်းပြောနေတဲ့ညီလေး မင်းက ဖူးဖူး\nမင်းသားက တေးသွားပေါ်မှာ ဟာ ချီး မိုက်တယ် မိုက်တယ်\nမုန်းတဲ့သူ မုန်းနေတယ် ငါ မရည်ရွယ်ပါဘူး\nငိုနေတယ် သူတို့ ငိုနေတယ်မင်း မင်းဘယ်သူလဲ\nVannex တေးသွားနဲ့ဂေါ်နေပြီ အဆင်သင့်ပြင်\nမင်း အဲ့အဝတ်အစားကို ဂရုစိုက်တယ်မလား\nခုငါနိုင်နေပြီ ဘယ်တော့မှပြန်လာဖို့ မကြိုးစားနဲ့\nငါ့ကို မှီအောင်သာ ကြိုးစား\n\nငါပြန်လာပြီ အရှိန်အဟုန်နဲ့\nRoddy Rich လို အောက်ကနေ ငါပိုင်တယ်\nမရဘူးပြောလို့ ငါ risk ယူလိုက်တယ်\nမင်းကို ငါ့အမုန်းစာရင်းမှာ ထည့်ထားလိုက်ပြီ\nဘာလို့လဲဆိုတော့ မင်းက လေးစားမှုနဲ့ မထိုက်တန်လို့\nအဲ့တော့ မင်းတင်ကို လှုပ်လိုက်အုံး\nဒီ ဂျာစီ ထိတယ် ဒီဂျာစီ တိုက်တယ်\nChris ထဲကလိုပဲ ငါ့ကိုယ်ငါ ကုနေတယ်\n\nVannex မင်းဒီလောက် ရူးရူးမိုက်မိုက် မလှုပ်နဲ့\nဘာလို့လဲ မင်းလုပ်တာ သူတို့ မျက်နှာပျက်နေပြီ\nဟာ ဘာပြောချင်တာလဲ\nအဲ့ မ ရက်တတ်တဲ့ ရက်ပါတွေ\nအဲ့ ထောင်ချောက်မဆင်တတ်တဲ့ ထောင်ချောက်ဆင်တဲ့လူတွေ\nအဲ့ တကယ့်လိမ်မယ့် လူလိမ်တွေ\nတချို့ သိပ်မမုန်းတဲ့ မုန်းတဲ့လူတွေ\nသူတို့လိုချင်တာ နေရာပါပဲ\n\nဆေးလာချရဲတဲ့ မင်းရဲ့ သတ္တိ\nမိုက်ခ် မက်စ် ပန်ဂ် က ငါရဲ့ ဘရို\nငါ့နောက်ကျောမှာ အောက်ချင်းငှက်တွေ ရှိတယ်\nM ဆိုတာ မီဇိုကောင်လေးတွေ လာ သွားမယ်!!!\n\nဆေးလာချရဲတဲ့ မင်းရဲ့ သတ္တိ\nမိုက်ခ် မက်စ် ပန်ဂ် က ငါရဲ့ ဘရို\nငါ့နောက်ကျောမှာ အောက်ချင်းငှက်တွေ ရှိတယ်\nM ဆိုတာ မီဇိုကောင်လေးတွေ လာ သွားမယ်!!!\n\nငါ့အတင်းပြောနေတဲ့ညီလေး မင်းက ဖူးဖူး\nမင်းသားက တေးသွားပေါ်မှာ ဟာ ချီး မိုက်တယ် မိုက်တယ်\nမုန်းတဲ့သူ မုန်းနေတယ် ငါ မရည်ရွယ်ပါဘူး\nငိုနေတယ် သူတို့ ငိုနေတယ်မင်း မင်းဘယ်သူလဲ\nVannex တေးသွားနဲ့ဂေါ်နေပြီ အဆင်သင့်ပြင်\nမင်း အဲ့အဝတ်အစားကို ဂရုစိုက်တယ်မလား\nခုငါနိုင်နေပြီ ဘယ်တော့မှပြန်လာဖို့ မကြိုးစားနဲ့\nငါ့ကို မှီအောင်သာ ကြိုးစား\n\nငါ့အတင်းပြောနေတဲ့ညီလေး မင်းက ဖူးဖူး\nမင်းသားက တေးသွားပေါ်မှာ ဟာ ချီး မိုက်တယ် မိုက်တယ်\nမုန်းတဲ့သူ မုန်းနေတယ် ငါ မရည်ရွယ်ပါဘူး\nငိုနေတယ် သူတို့ ငိုနေတယ်မင်း မင်းဘယ်သူလဲ\nVannex တေးသွားနဲ့ဂေါ်နေပြီ အဆင်သင့်ပြင်\nမင်း အဲ့အဝတ်အစားကို ဂရုစိုက်တယ်မလား\nခုငါနိုင်နေပြီ ဘယ်တော့မှပြန်လာဖို့ မကြိုးစားနဲ့\nငါ့ကို မှီအောင်သာ ကြိုးစား\n\nနယူယောက် drill လား\nယူကေ drill လား\nမဟုတ်ဘူး ဘရို ဒါက မြန်မာ drill\nဒါလုံးဝ အတည် သူတို့ သိပါစေ\nခုက ငါတို့ အချိန် ခုက ဖော်ထုတ်ပြသချိန်\n\nနယူယောက် drill လား\nယူကေ drill လား\nမဟုတ်ဘူး ဘရို ဒါက မြန်မာ drill\nဒါလုံးဝ အတည် သူတို့ သိပါစေ\nခုက ငါတို့ အချိန် ခုက ဖော်ထုတ်ပြသချိန်\n\nငါ့အတင်းပြောနေတဲ့ညီလေး မင်းက ဖူးဖူး\nမင်းသားက တေးသွားပေါ်မှာ ဟာ ချီး မိုက်တယ် မိုက်တယ်\nမုန်းတဲ့သူ မုန်းနေတယ် ငါ မရည်ရွယ်ပါဘူး\nငိုနေတယ် သူတို့ ငိုနေတယ်မင်း မင်းဘယ်သူလဲ\nVannex တေးသွားနဲ့ဂေါ်နေပြီ အဆင်သင့်ပြင်\nမင်း အဲ့အဝတ်အစားကို ဂရုစိုက်တယ်မလား\nခုငါနိုင်နေပြီ ဘယ်တော့မှပြန်လာဖို့ မကြိုးစားနဲ့\nငါ့ကို မှီအောင်သာ ကြိုးစား\n\nဆေးလာချရဲတဲ့ မင်းရဲ့ သတ္တိ\nမိုက်ခ် မက်စ် ပန်ဂ် က ငါရဲ့ ဘရို\nငါ့နောက်ကျောမှာ အောက်ချင်းငှက်တွေ ရှိတယ်\nM ဆိုတာ မီဇိုကောင်လေးတွေ လာ သွားမယ်!!!\n\nဆေးလာချရဲတဲ့ မင်းရဲ့ သတ္တိ\nမိုက်ခ် မက်စ် ပန်ဂ် က ငါရဲ့ ဘရို\nငါ့နောက်ကျောမှာ အောက်ချင်းငှက်တွေ ရှိတယ်\nM ဆိုတာ မီဇိုကောင်လေးတွေ လာ သွားမယ်!!!\n",
  "meaning": "Prince Vannex on the beat let's go\nTalking bout me lil bro yo what\nLil bro you a foofoo\nAye aye\nA re A re\nPrince on the beat oh sh*t what\nLet's go Let's go\n\nTalking bout me lil bro you a foofoo\nPrince on the beat oh sh*t it's coo cool\nHaters mad like bro I don't mean to\nCrying they crying bro who you?\nVannex on the beat yo bro get ready\nDo you not care about that outfit?\nNow we winning don't ever try to come back\nD*ckride just try to get to my level!\n\nTalking bout me lil bro you a foofoo\nPrince on the beat oh sh*t it's coo cool\nHaters mad like bro I don't mean to\nCrying they crying bro who you?\nVannex on the beat yo bro get ready\nDo you not care about that outfit?\nNow we winning don't ever try to come back\nD*ckride just try to get to my level!\n\nI’m back with the heat Yea \nI own this shit from down below like Roddy Rich \nSaid I can’t so I take this risk\nI’ll put you down on my haters List\nCause u do not deserve no diss\nSo go on and shake that hip\nThis jersey drill this jersey hit\nI’m healing myself likes the one from Chris\n\nVannex u don’t gotta move this mad\nWhy??? U making them look so bad\nHuh??? What do u mean by that?? \nThem drill rappers who really can’t rap \nThem trap trappers who really don’t trap\nThem cap cappers who really gon cap \nSome of the haters who really don’t hate\nThey just wanted the spot or they wanted the place\n\nShit you dare to drop d*pe like Blow \nMike Mas Peng my dawg my Bros\nHornBills got my back 24\nM for MIZO boyz let’s go!!!\n\nShit you dare to drop d*pe like Blow \nMike Mas Peng my dawg my Bros\nHornBills got my back 24\nM for MIZO boyz let’s go!!!\n\nTalking bout me lil bro you a foofoo\nPrince on the beat oh sh*t it's coo cool\nHaters mad like bro I don't mean to\nCrying they crying bro who you?\nVannex on the beat yo bro get ready\nDo you not care about that outfit?\nNow we winning don't ever try to come back\nD*ckride just try to get to my level!\n\nTalking bout me lil bro you a foofoo\nPrince on the beat oh sh*t it's coo cool\nHaters mad like bro I don't mean to\nCrying they crying bro who you?\nVannex on the beat yo bro get ready\nDo you not care about that outfit?\nNow we winning don't ever try to come back\nD*ckride just try to get to my level!\n\nNew York Drill?\nUk Drill?\nNah Bro this MYANMAR Drill\nLet them know that this shyt getting real\nIs our time yea is time to reveal\n\nNewYork Drill?\nUk Drill?\nNah Bro this BURMA Drill\nLet them know that this shyt getting real\nIs our time yea is time to reveal\n\nTalking bout me lil bro you a foofoo\nPrince on the beat oh sh*t it's coo cool\nHaters mad like bro I don't mean to\nCrying they crying bro who you?\nVannex on the beat yo bro get ready\nDo you not care about that outfit?\nNow we winning don't ever try to come back\nD*ckride just try to get to my level!\n\nShit you dare to drop d*pe like Blow \nMike Mas Peng my dawg my Bros\nHornBills got my back 24\nM for MIZO boyz let’s go!!!\n\nShit you dare to drop d*pe like Blow \nMike Mas Peng my dawg my Bros\nHornBills got my back 24\nM for MIZO boyz let’s go!!!\n"
}