{
  "mmid": 81,
  "songName": "Kyway Par Say (ကြွေပါစေ)",
  "artistName": "R Zarni",
  "albumName": "Pan Chwae Tae Lay",
  "genre": "Pop",
  "spotifyTrackId": "4C6LfXgH9DAPcoQoTvtDcg",
  "imageLink": "https://i.scdn.co/image/ab67616d00001e0206fdcd6ec639f872b75d97c9",
  "appleMusicLink": "https://music.apple.com/ca/song/kyway-par-say/1477287464",
  "spotifyLink": "https://open.spotify.com/track/4C6LfXgH9DAPcoQoTvtDcg",
  "youtubeLink": "https://www.youtube.com/watch?v=kMyLxgzt8Cw",
  "about": "\"Kyway Par Say\", meaning \"Let It Fall\" is a Burmese song about embracing loss and finding peace in letting go of past burdens and sorrows",
  "whenToListen": "When you need soothing music for quiet nights of thinking about life's changes and the beauty of moving on.",
  "lyrics": "ဆုံးရှုံးခြင်းသာ ရရှိခဲ့ပြီ\nဒါကို အမှားအယွင်းတစ်ခုလို မထင်ချင်ပါ\nလမ်းဟောင်းလေးမှာ နှလုံးသားတစ်ခုရဲ့\nတီးတိုးငိုသံ ကြားနိုင်မလား\n\nအိပ်မက်တစ်ခုဟာ ပြီးဆုံးခဲ့ပြီ\nလောင်မြိုက်ခြင်းနဲ့\nဘဝကို အဆုံးသတ်မသွားပါ\nဆုံနိုင်ခွင့်ရှိလည်း ဆုံချင်သေးပါရဲ့\nဒီလမ်းလေး ပေါ်မှာ\n\nရုန်း...မထွက်ချင်တော့ပါ\nစွဲလန်းခြင်းကို မြတ်နိုးစွာ\nစီတ်ငြိမ်စွာ ခံစားရင်း\nဘဝကို ကျေနပ်ရမှာပါ\n\nဘာကိုမျှော်လင့်လို့ ဆုပ်ကိုင်ထားရမလဲ\nတစ်ယောက်တည်း အထီးကျန်နေပြီပဲ\nဘာကိုမကျေနပ်လို့ ဟစ်အော်နိုင်ဦးမလဲ\nစကားတွေရှာလည်း မရနိုင်ခဲ့\nဘယ်ကိုထွက်ပြေးလို့\nလွတ်မြှောက်ခြင်းရှိမယ်\nနှောင်ကြိုးများကို မဖြေနိုင်ခဲ့\nငါဟာသေဆုံးသော ရွက်ကြွေတွေဘဝလို\nလမ်းဟောင်းလေးပေါ်မှာ\nကြွေနေပါစေတော့ ရှုံးပြီးသား\n\nဆုံးရှုံးခြင်းသာ ရရှိခဲ့ပြီ\nဒါကို အမှားအယွင်းတစ်ခုလို မထင်ချင်ပါ\nလမ်းဟောင်းလေးမှာ နှလုံးသားတစ်ခုရဲ့\nတီးတိုးငိုသံ ကြားနိုင်မလား\n\nအိပ်မက်တစ်ခုဟာ ပြီးဆုံးခဲ့ပြီ\nလောင်မြိုက်ခြင်းနဲ့\nဘဝကို အဆုံးသတ်မသွားပါ\nဆုံနိုင်ခွင့်ရှိလည်း ဆုံချင်သေးပါရဲ့\nဒီလမ်းလေး ပေါ်မှာ\n\nရုန်း...မထွက်ချင်တော့ပါ\nစွဲလန်းခြင်းကို မြတ်နိုးစွာ\nစီတ်ငြိမ်စွာ ခံစားရင်း\nဘဝကို ကျေနပ်ရမှာပါ\n\nဘာကိုမျှော်လင့်လို့ ဆုပ်ကိုင်ထားရမလဲ\nတစ်ယောက်တည်း အထီးကျန်နေပြီပဲ\nဘာကိုမကျေနပ်လို့ ဟစ်အော်နိုင်ဦးမလဲ\nစကားတွေရှာလည်း မရနိုင်ခဲ့\nဘယ်ကိုထွက်ပြေးလို့\nလွတ်မြှောက်ခြင်းရှိမယ်\nနှောင်ကြိုးများကို မဖြေနိုင်ခဲ့\nငါဟာသေဆုံးသော ရွက်ကြွေတွေဘဝလို\nလမ်းဟောင်းလေးပေါ်မှာ\nကြွေနေပါစေတော့ ရှုံးပြီးသား\n\nငါဟာ သေဆုံးသော ရွက်ကြွေတွေဘဝလို\nလမ်းဟောင်းလေးပေါ်မှာ\nကြွေနေပါစေတော့ ရှုံးပြီးသား\n",
  "romanized": "Sone shone chin thar ya shi khae b\nDar ko a hmar a ywin ta khu lo htin chin par\nLann haung lay hmar hna lone thar ta khu yae \nTee toe ngo than kyar nai ma lar\n\nEain mat ta khu har pee sone khae b\nLaun myite chin nae\nBawa ko a sone thet ma thwar bar\nSone nai khwint shi lae sone chin thay bar yae\nDi lann lay por hmar\n\nYone... ma htwat chin tot par\nSwal lann chin ko myat noe swar\nSate nyain swar khan sarr yin\nBawa ko kyay nat ya hmar bar\n\nBar ko myaw lint loh sote kine htar ya ma lae\nTa yout htal a htee kyan nay b bae\nBar ko me kyay net loh hit or nai own ma lae\nZakar tway shar lae ma ya nai khae\nBal ko htwat pyay loh\nLoot myauk chin shi mal\nNhaun kyoe myar ko me pyay nai khae\nNgar har thay sone thaw ywat kyway tway bawa lo\nLan haun lay por hmar\nKyway nay par say tot shone pee thar\n\nSone shone chin thar ya shi khae b\nDar ko a hmar a ywin ta khu lo htin chin par\nLann haung lay hmar hna lone thar ta khu yae \nTee toe ngo than kyar nai ma lar\n\nEain mat ta khu har pee sone khae b\nLaun myite chin nae\nBawa ko a sone thet ma thwar bar\nSone nai khwint shi lae sone chin thay bar yae\nDi lann lay por hmar\n\nYone... ma htwat chin tot par\nSwal lann chin ko myat noe swar\nSate nyain swar khan sarr yin\nBawa ko kyay nat ya hmar bar\n\nBar ko myaw lint loh sote kine htar ya ma lae\nTa yout htal a htee kyan nay b bae\nBar ko me kyay net loh hit or nai own ma lae\nZakar tway shar lae ma ya nai khae\nBal ko htwat pyay loh\nLoot myauk chin shi mal\nNhaun kyoe myar ko me pyay nai khae\nNgar har thay sone thaw ywat kyway tway bawa lo\nLan haun lay por hmar\nKyway nay par say tot shone pee thar\n\nNgar har thay sone thaw ywat kyway tway bawa lo\nLan haun lay por hmar\nKyway nay par say tot shone pee thar\n",
  "burmese": "ဆုံးရှုံးခြင်းသာ ရရှိခဲ့ပြီ\nဒါကို အမှားအယွင်းတစ်ခုလို မထင်ချင်ပါ\nလမ်းဟောင်းလေးမှာ နှလုံးသားတစ်ခုရဲ့\nတီးတိုးငိုသံ ကြားနိုင်မလား\n\nအိပ်မက်တစ်ခုဟာ ပြီးဆုံးခဲ့ပြီ\nလောင်မြိုက်ခြင်းနဲ့\nဘဝကို အဆုံးသတ်မသွားပါ\nဆုံနိုင်ခွင့်ရှိလည်း ဆုံချင်သေးပါရဲ့\nဒီလမ်းလေး ပေါ်မှာ\n\nရုန်း...မထွက်ချင်တော့ပါ\nစွဲလန်းခြင်းကို မြတ်နိုးစွာ\nစီတ်ငြိမ်စွာ ခံစားရင်း\nဘဝကို ကျေနပ်ရမှာပါ\n\nဘာကိုမျှော်လင့်လို့ ဆုပ်ကိုင်ထားရမလဲ\nတစ်ယောက်တည်း အထီးကျန်နေပြီပဲ\nဘာကိုမကျေနပ်လို့ ဟစ်အော်နိုင်ဦးမလဲ\nစကားတွေရှာလည်း မရနိုင်ခဲ့\nဘယ်ကိုထွက်ပြေးလို့\nလွတ်မြှောက်ခြင်းရှိမယ်\nနှောင်ကြိုးများကို မဖြေနိုင်ခဲ့\nငါဟာသေဆုံးသော ရွက်ကြွေတွေဘဝလို\nလမ်းဟောင်းလေးပေါ်မှာ\nကြွေနေပါစေတော့ ရှုံးပြီးသား\n\nဆုံးရှုံးခြင်းသာ ရရှိခဲ့ပြီ\nဒါကို အမှားအယွင်းတစ်ခုလို မထင်ချင်ပါ\nလမ်းဟောင်းလေးမှာ နှလုံးသားတစ်ခုရဲ့\nတီးတိုးငိုသံ ကြားနိုင်မလား\n\nအိပ်မက်တစ်ခုဟာ ပြီးဆုံးခဲ့ပြီ\nလောင်မြိုက်ခြင်းနဲ့\nဘဝကို အဆုံးသတ်မသွားပါ\nဆုံနိုင်ခွင့်ရှိလည်း ဆုံချင်သေးပါရဲ့\nဒီလမ်းလေး ပေါ်မှာ\n\nရုန်း...မထွက်ချင်တော့ပါ\nစွဲလန်းခြင်းကို မြတ်နိုးစွာ\nစီတ်ငြိမ်စွာ ခံစားရင်း\nဘဝကို ကျေနပ်ရမှာပါ\n\nဘာကိုမျှော်လင့်လို့ ဆုပ်ကိုင်ထားရမလဲ\nတစ်ယောက်တည်း အထီးကျန်နေပြီပဲ\nဘာကိုမကျေနပ်လို့ ဟစ်အော်နိုင်ဦးမလဲ\nစကားတွေရှာလည်း မရနိုင်ခဲ့\nဘယ်ကိုထွက်ပြေးလို့\nလွတ်မြှောက်ခြင်းရှိမယ်\nနှောင်ကြိုးများကို မဖြေနိုင်ခဲ့\nငါဟာသေဆုံးသော ရွက်ကြွေတွေဘဝလို\nလမ်းဟောင်းလေးပေါ်မှာ\nကြွေနေပါစေတော့ ရှုံးပြီးသား\n\nငါဟာ သေဆုံးသော ရွက်ကြွေတွေဘဝလို\nလမ်းဟောင်းလေးပေါ်မှာ\nကြွေနေပါစေတော့ ရှုံးပြီးသား\n",
  "meaning": "All that I received was a loss,\nI don't want to think of this as just a mistake.\nOn this old path, can you hear\nthe faint crying of a heart?\n\nA dream has ended,\nNot ending this life,\nwith just burning.\nI still want to meet you if there is a chance,\nright on this path.\n\nI don't want to escape anymore,\nCherishing the obsession,\nQuietly feeling,\nI have to be satisfied with life.\n\nWhat do I hope and hold onto?\nAlone, left behind,\nWhy can't I be satisfied, what can I shout?\nI couldn't find the words,\nWhere can I run to\nwhere there is freedom?\nCouldn't untie the bonds,\nI am like dead leaves,\nCrushed on this old path,\nalready lost.\n\nAll that I received was a loss,\nI don't want to think of this as just a mistake.\nOn this old path, can you hear\nthe faint crying of a heart?\n\nA dream has ended,\nNot ending this life,\nwith just burning.\nI still want to meet you if there is a chance,\nright on this path.\n\nI don't want to escape anymore,\nCherishing the obsession,\nQuietly feeling,\nI have to be satisfied with life.\n\nWhat do I hope and hold onto?\nAlone, left behind,\nWhy can't I be satisfied, what can I shout?\nI couldn't find the words,\nWhere can I run to\nwhere there is freedom?\nCouldn't untie the bonds,\nI am like dead leaves,\nCrushed on this old path,\nalready lost.\n\nI am like dead leaves,\nCrushed on this old path,\nalready lost.\n"
}